jb_manager_bot/__init__.py
jb_manager_bot/abstract_fsm.py
jb_manager_bot/data_models.py
jb_manager_bot/parsers/__init__.py
jb_manager_bot/parsers/option_parser/__init__.py
jb_manager_bot/parsers/utils.py
jb_manager_bot/tests/neocarwash.py
jb_manager_bot/tests/test_abstractfsm.py
jb_manager_bot/tests/test_parser.py
jb_manager_bot-0.2.4.dist-info/METADATA
jb_manager_bot-0.2.4.dist-info/WHEEL
jb_manager_bot-0.2.4.dist-info/RECORD
