Metadata-Version: 2.1
Name: jb-manager-bot
Version: 0.2.4
Summary: Bot for JugalBandi Manager
Author: Shrey Pandey
Author-email: shreypandey1509@gmail.com
Requires-Python: >=3.10,<4.0
Classifier: Programming Language :: Python :: 3
Classifier: Programming Language :: Python :: 3.10
Classifier: Programming Language :: Python :: 3.11
Classifier: Programming Language :: Python :: 3.12
Requires-Dist: azure-identity (>=1.21.0,<2.0.0)
Requires-Dist: openai (>=1.12.0,<2.0.0)
Requires-Dist: pydantic (>=2.6.1,<3.0.0)
Requires-Dist: transitions (>=0.9.0,<0.10.0)
